vkmsg/__init__.py
vkmsg/errors.py
vkmsg/helpers.py
vkmsg/vk_client.py
vkmsg/models/__init__.py
vkmsg/models/keyboards.py
vkmsg/models/messages.py
vkmsg/models/requests.py
vkmsg-0.1.2.dist-info/LICENSE
vkmsg-0.1.2.dist-info/METADATA
vkmsg-0.1.2.dist-info/WHEEL
vkmsg-0.1.2.dist-info/top_level.txt
vkmsg-0.1.2.dist-info/RECORD
